{
  "data": [
    {
      "userId": 1,
      "name": "김민대",
      "position": "대표",
      "email": "mindea@77cm.co.kr",
      "password": "CEO12345",
      "phone": "010-7107-6358",
      "birth": "1980-02-16",
      "dept": "C-level",
      "leftVaca": 13,
      "admin": true,
      "img": "/server/images/profile/1.jpg"
    },
    {
      "userId": 2,
      "name": "김대영",
      "position": "부장",
      "email": "dev.meryoung@77cm.co.kr",
      "password": "ajdud1",
      "phone": "010-4756-2128",
      "birth": "1996-09-19",
      "dept": "개발팀",
      "leftVaca": 3,
      "admin": true,
      "img": "/server/images/profile/2.jpg"
    },
    {
      "userId": 3,
      "name": "배하은",
      "position": "과장",
      "email": "haruyam15@77cm.co.kr",
      "password": "1234",
      "phone": "010-2767-9609",
      "birth": "1986-12-21",
      "dept": "개발팀",
      "leftVaca": 9,
      "admin": true,
      "img": "/server/images/profile/3.jpg"
    },
    {
      "userId": 4,
      "name": "송진",
      "position": "대리",
      "email": "sjgaru@77cm.co.kr",
      "password": "1234",
      "phone": "010-8114-4278",
      "birth": "1955-03-02",
      "dept": "개발팀",
      "leftVaca": 1,
      "admin": true,
      "img": "/server/images/profile/4.jpg"
    },
    {
      "userId": 5,
      "name": "박지영",
      "position": "차장",
      "email": "jizero27@77cm.co.kr",
      "password": "a2345",
      "phone": "010-4344-9545",
      "birth": "1996-11-04",
      "dept": "개발팀",
      "leftVaca": 9,
      "admin": true,
      "img": "/server/images/profile/5.jpg"
    },
    {
      "userId": 6,
      "name": "김해민",
      "position": "부장",
      "email": "heymin@77cm.co.kr",
      "password": "1234",
      "phone": "010-1606-4149",
      "birth": "1994-01-02",
      "dept": "운영팀",
      "leftVaca": 3,
      "admin": false,
      "img": "/server/images/profile/6.jpg"
    },
    {
      "userId": 7,
      "name": "유현수",
      "position": "차장",
      "email": "seojunbag@77cm.co.kr",
      "password": "1234",
      "phone": "010-6440-7770",
      "birth": "1962-04-08",
      "dept": "마케팅팀",
      "leftVaca": 17,
      "admin": false,
      "img": "/server/images/profile/7.jpg"
    },
    {
      "userId": 8,
      "name": "김민채",
      "position": "대리",
      "email": "hayun94@77cm.co.kr",
      "password": "1aSMpkBs",
      "phone": "010-4119-4551",
      "birth": "2003-08-19",
      "dept": "마케팅팀",
      "leftVaca": 3,
      "admin": false,
      "img": null
    },
    {
      "userId": 9,
      "name": "이규성",
      "position": "과장",
      "email": "osugja@77cm.co.kr",
      "password": "4NUPD6Ll",
      "phone": "010-4464-3177",
      "birth": "1962-09-18",
      "dept": "인사팀",
      "leftVaca": 3,
      "admin": false,
      "img": "/server/images/profile/9.jpg"
    },
    {
      "userId": 10,
      "name": "시아준수",
      "position": "대리",
      "email": "hyeonjubag@77cm.co.kr",
      "password": "c33LaWLU",
      "phone": "010-3458-3972",
      "birth": "1955-06-24",
      "dept": "재무팀",
      "leftVaca": 9,
      "admin": false,
      "img": "/server/images/profile/10.jpg"
    },
    {
      "userId": 11,
      "name": "이수영",
      "position": "대리",
      "email": "hayungim@77cm.co.kr",
      "password": "o5CtMasb",
      "phone": "010-3772-4380",
      "birth": "1962-03-30",
      "dept": "개발팀",
      "leftVaca": 19,
      "admin": false,
      "img": "/server/images/profile/11.jpg"
    },
    {
      "userId": 12,
      "name": "장선영",
      "position": "부장",
      "email": "jeonghoseo@77cm.co.kr",
      "password": "RKn3lXnp",
      "phone": "010-9672-4406",
      "birth": "1958-01-22",
      "dept": "마케팅팀",
      "leftVaca": 4,
      "admin": false,
      "img": "/server/images/profile/12.jpg"
    },
    {
      "userId": 13,
      "name": "이미숙",
      "position": "CTO",
      "email": "anjunyeong@77cm.co.kr",
      "password": "sqf1fqEj",
      "phone": "010-2594-5588",
      "birth": "1992-10-12",
      "dept": "C-level",
      "leftVaca": 12,
      "admin": false,
      "img": "/server/images/profile/13.jpg"
    },
    {
      "userId": 14,
      "name": "허지우",
      "position": "사원",
      "email": "egim@77cm.co.kr",
      "password": "v2ERt9LD",
      "phone": "010-3615-1216",
      "birth": "1992-07-07",
      "dept": "영업팀",
      "leftVaca": 15,
      "admin": false,
      "img": null
    },
    {
      "userId": 15,
      "name": "나현숙",
      "position": "대리",
      "email": "seohyeon93@77cm.co.kr",
      "password": "7HSYnwSg",
      "phone": "010-2130-7575",
      "birth": "1980-06-24",
      "dept": "개발팀",
      "leftVaca": 6,
      "admin": false,
      "img": "/server/images/profile/15.jpg"
    },
    {
      "userId": 16,
      "name": "문상훈",
      "position": "사원",
      "email": "yunyeweon@77cm.co.kr",
      "password": "Om7R9dyu",
      "phone": "010-504-2283",
      "birth": "1977-07-02",
      "dept": "인사팀",
      "leftVaca": 18,
      "admin": false,
      "img": "/server/images/profile/16.jpg"
    },
    {
      "userId": 17,
      "name": "선우정아",
      "position": "대리",
      "email": "caeweoncoe@77cm.co.kr",
      "password": "3Te2Mq7p",
      "phone": "010-7498-3547",
      "birth": "1984-08-20",
      "dept": "영업팀",
      "leftVaca": 13,
      "admin": false,
      "img": "/server/images/profile/17.jpg"
    },
    {
      "userId": 18,
      "name": "강준호",
      "position": "과장",
      "email": "sanghun89@77cm.co.kr",
      "password": "3DlebUnL",
      "phone": "010-4197-3243",
      "birth": "1998-01-09",
      "dept": "재무팀",
      "leftVaca": 3,
      "admin": false,
      "img": "/server/images/profile/18.jpg"
    },
    {
      "userId": 19,
      "name": "차민지",
      "position": "부장",
      "email": "ngim@77cm.co.kr",
      "password": "0AOEn1jR",
      "phone": "010-9593-5475",
      "birth": "1978-10-20",
      "dept": "개발팀",
      "leftVaca": 15,
      "admin": false,
      "img": "/server/images/profile/19.jpg"
    },
    {
      "userId": 20,
      "name": "나주원",
      "position": "대리",
      "email": "xjeon@77cm.co.kr",
      "password": "Hb9tAYrf",
      "phone": "010-6799-2799",
      "birth": "1961-11-17",
      "dept": "개발팀",
      "leftVaca": 19,
      "admin": false,
      "img": "/server/images/profile/20.jpg"
    },
    {
      "userId": 21,
      "name": "박서현",
      "position": "과장",
      "email": "bagminjun@77cm.co.kr",
      "password": "u3I0MQCw",
      "phone": "010-5853-7865",
      "birth": "1995-09-05",
      "dept": "인사팀",
      "leftVaca": 6,
      "admin": false,
      "img": null
    },
    {
      "userId": 22,
      "name": "이미숙",
      "position": "COO",
      "email": "wgo@77cm.co.kr",
      "password": "4XaxgV3v",
      "phone": "010-4765-6954",
      "birth": "1975-10-28",
      "dept": "C-level",
      "leftVaca": 11,
      "admin": false,
      "img": "/server/images/profile/22.jpg"
    },
    {
      "userId": 23,
      "name": "고미경",
      "position": "부장",
      "email": "xryu@77cm.co.kr",
      "password": "1WUWrJIi",
      "phone": "010-4470-9567",
      "birth": "1973-07-21",
      "dept": "마케팅팀",
      "leftVaca": 12,
      "admin": false,
      "img": "/server/images/profile/23.jpg"
    },
    {
      "userId": 24,
      "name": "이지은",
      "position": "차장",
      "email": "tgang@77cm.co.kr",
      "password": "bK0E4Rzv",
      "phone": "010-2778-8439",
      "birth": "1976-08-17",
      "dept": "개발팀",
      "leftVaca": 4,
      "admin": false,
      "img": "/server/images/profile/24.jpg"
    },
    {
      "userId": 25,
      "name": "김성민",
      "position": "차장",
      "email": "yi@77cm.co.kr",
      "password": "7CiJSDWt",
      "phone": "010-1441-3557",
      "birth": "1996-08-25",
      "dept": "개발팀",
      "leftVaca": 13,
      "admin": false,
      "img": "/server/images/profile/25.jpg"
    },
    {
      "userId": 26,
      "name": "박건우",
      "position": "차장",
      "email": "boram86@77cm.co.kr",
      "password": "fn3v8Zac",
      "phone": "010-8324-6723",
      "birth": "1989-10-18",
      "dept": "인사팀",
      "leftVaca": 6,
      "admin": false,
      "img": "/server/images/profile/26.jpg"
    },
    {
      "userId": 27,
      "name": "박순옥",
      "position": "차장",
      "email": "goyeongmi@77cm.co.kr",
      "password": "0GD42Eon",
      "phone": "010-8214-6136",
      "birth": "1990-06-29",
      "dept": "개발팀",
      "leftVaca": 11,
      "admin": false,
      "img": "/server/images/profile/27.jpg"
    },
    {
      "userId": 28,
      "name": "김명숙",
      "position": "부장",
      "email": "myeongsuggim@77cm.co.kr",
      "password": "0Zm5SsO",
      "phone": "010-504-2892",
      "birth": "1989-04-06",
      "dept": "재무팀",
      "leftVaca": 4,
      "admin": false,
      "img": "/server/images/profile/28.jpg"
    },
    {
      "userId": 29,
      "name": "이명숙",
      "position": "과장",
      "email": "seojun87@77cm.co.kr",
      "password": "H2K6RKyu",
      "phone": "010-9739-3409",
      "birth": "1988-11-10",
      "dept": "재무팀",
      "leftVaca": 10,
      "admin": false,
      "img": "/server/images/profile/29.jpg"
    },
    {
      "userId": 30,
      "name": "송건우",
      "position": "부장",
      "email": "yejingim@77cm.co.kr",
      "password": "ScN8AhM1",
      "phone": "010-5689-5619",
      "birth": "1978-07-05",
      "dept": "영업팀",
      "leftVaca": 6,
      "admin": false,
      "img": null
    },
    {
      "userId": 31,
      "name": "김영수",
      "position": "사원",
      "email": "ujinhan@77cm.co.kr",
      "password": "On7o2NFv",
      "phone": "010-9481-7783",
      "birth": "1992-08-12",
      "dept": "재무팀",
      "leftVaca": 7,
      "admin": false,
      "img": null
    },
    {
      "userId": 32,
      "name": "김진우",
      "position": "차장",
      "email": "ieunyeong@77cm.co.kr",
      "password": "pR1ztAgw",
      "phone": "010-4796-9810",
      "birth": "1967-05-20",
      "dept": "인사팀",
      "leftVaca": 9,
      "admin": false,
      "img": null
    },
    {
      "userId": 33,
      "name": "김순옥",
      "position": "대리",
      "email": "syun@77cm.co.kr",
      "password": "Gce1RskH",
      "phone": "010-3850-2513",
      "birth": "1996-06-25",
      "dept": "개발팀",
      "leftVaca": 7,
      "admin": false,
      "img": null
    },
    {
      "userId": 34,
      "name": "이명자",
      "position": "차장",
      "email": "msin@77cm.co.kr",
      "password": "h0JP5hGE",
      "phone": "010-5461-1126",
      "birth": "1990-08-30",
      "dept": "마케팅팀",
      "leftVaca": 18,
      "admin": false,
      "img": null
    },
    {
      "userId": 35,
      "name": "차준호",
      "position": "과장",
      "email": "seungmin66@77cm.co.kr",
      "password": "4WILRuEe",
      "phone": "010-9212-3988",
      "birth": "1987-07-31",
      "dept": "개발팀",
      "leftVaca": 13,
      "admin": false,
      "img": null
    },
    {
      "userId": 36,
      "name": "김채원",
      "position": "대리",
      "email": "jangsugja@77cm.co.kr",
      "password": "86MQEGbj",
      "phone": "010-4393-2348",
      "birth": "1982-05-21",
      "dept": "마케팅팀",
      "leftVaca": 20,
      "admin": false,
      "img": null
    },
    {
      "userId": 37,
      "name": "김영식",
      "position": "CHO",
      "email": "yunjunho@77cm.co.kr",
      "password": "CgU32Myw",
      "phone": "010-7859-1096",
      "birth": "1979-06-03",
      "dept": "C-level",
      "leftVaca": 0,
      "admin": false,
      "img": null
    },
    {
      "userId": 38,
      "name": "전영환",
      "position": "차장",
      "email": "isangceol@77cm.co.kr",
      "password": "6GtqDzDp",
      "phone": "010-3573-6983",
      "birth": "1965-08-14",
      "dept": "마케팅팀",
      "leftVaca": 8,
      "admin": false,
      "img": null
    },
    {
      "userId": 39,
      "name": "류은지",
      "position": "대리",
      "email": "hwangareum@77cm.co.kr",
      "password": "2mySwyg9",
      "phone": "010-3290-8158",
      "birth": "1974-08-14",
      "dept": "개발팀",
      "leftVaca": 17,
      "admin": false,
      "img": null
    },
    {
      "userId": 40,
      "name": "허영진",
      "position": "차장",
      "email": "caeweonji@77cm.co.kr",
      "password": "jv5vOQb8",
      "phone": "010-5350-8026",
      "birth": "1971-01-10",
      "dept": "개발팀",
      "leftVaca": 16,
      "admin": false,
      "img": null
    },
    {
      "userId": 41,
      "name": "최은지",
      "position": "CFO",
      "email": "rgim@77cm.co.kr",
      "password": "3OU0Veci",
      "phone": "010-4794-3458",
      "birth": "1996-05-03",
      "dept": "C-level",
      "leftVaca": 10,
      "admin": false,
      "img": null
    },
    {
      "userId": 42,
      "name": "임지훈",
      "position": "사원",
      "email": "si@77cm.co.kr",
      "password": "w91pH0Gd",
      "phone": "010-6460-5331",
      "birth": "1956-08-20",
      "dept": "재무팀",
      "leftVaca": 10,
      "admin": false,
      "img": null
    },
    {
      "userId": 43,
      "name": "김은주",
      "position": "과장",
      "email": "vbag@77cm.co.kr",
      "password": "Tn9TTvLj",
      "phone": "010-8430-8897",
      "birth": "1974-07-11",
      "dept": "인사팀",
      "leftVaca": 20,
      "admin": false,
      "img": null
    },
    {
      "userId": 44,
      "name": "김서연",
      "position": "사원",
      "email": "sunja80@77cm.co.kr",
      "password": "J4jM4VSp",
      "phone": "010-2434-8517",
      "birth": "1964-11-02",
      "dept": "인사팀",
      "leftVaca": 10,
      "admin": false,
      "img": null
    },
    {
      "userId": 45,
      "name": "김승현",
      "position": "대리",
      "email": "gimyeeun@77cm.co.kr",
      "password": "0my6Pcmc",
      "phone": "010-5555-2735",
      "birth": "1966-06-19",
      "dept": "인사팀",
      "leftVaca": 14,
      "admin": false,
      "img": null
    },
    {
      "userId": 46,
      "name": "박상호",
      "position": "사원",
      "email": "jia30@77cm.co.kr",
      "password": "yfH9Up4n",
      "phone": "010-2516-5342",
      "birth": "1986-05-01",
      "dept": "마케팅팀",
      "leftVaca": 4,
      "admin": false,
      "img": null
    },
    {
      "userId": 47,
      "name": "박옥순",
      "position": "부장",
      "email": "coegyeongja@77cm.co.kr",
      "password": "kb29MDup",
      "phone": "010-6028-3294",
      "birth": "1957-10-17",
      "dept": "마케팅팀",
      "leftVaca": 13,
      "admin": false,
      "img": null
    },
    {
      "userId": 48,
      "name": "김민재",
      "position": "차장",
      "email": "myeongjanam@77cm.co.kr",
      "password": "o9WPJaFH",
      "phone": "010-5668-3822",
      "birth": "1996-03-04",
      "dept": "개발팀",
      "leftVaca": 15,
      "admin": false,
      "img": null
    },
    {
      "userId": 49,
      "name": "박정남",
      "position": "대리",
      "email": "gimareum@77cm.co.kr",
      "password": "6KKVzXAa",
      "phone": "010-2862-7517",
      "birth": "1954-01-31",
      "dept": "재무팀",
      "leftVaca": 14,
      "admin": false,
      "img": null
    },
    {
      "userId": 50,
      "name": "진정남",
      "position": "차장",
      "email": "heoeungyeong@77cm.co.kr",
      "password": "TP35sPo7",
      "phone": "010-7346-9942",
      "birth": "1958-08-04",
      "dept": "인사팀",
      "leftVaca": 8,
      "admin": false,
      "img": null
    },
    {
      "userId": 51,
      "name": "박광수",
      "position": "부장",
      "email": "tjeong@77cm.co.kr",
      "password": "lY3tMTjv",
      "phone": "010-7053-7343",
      "birth": "1972-05-28",
      "dept": "인사팀",
      "leftVaca": 19,
      "admin": false,
      "img": "/server/images/profile/51.jpg"
    },
    {
      "userId": 52,
      "name": "이정훈",
      "position": "부장",
      "email": "bi@77cm.co.kr",
      "password": "k9yVn4gC",
      "phone": "010-4796-6827",
      "birth": "1966-03-20",
      "dept": "인사팀",
      "leftVaca": 16,
      "admin": false,
      "img": "/server/images/profile/52.jpg"
    },
    {
      "userId": 53,
      "name": "김지연",
      "position": "과장",
      "email": "gimmiyeong@77cm.co.kr",
      "password": "5KIpsVfH",
      "phone": "010-4153-7263",
      "birth": "1967-05-09",
      "dept": "마케팅팀",
      "leftVaca": 6,
      "admin": false,
      "img": null
    },
    {
      "userId": 54,
      "name": "김진우",
      "position": "차장",
      "email": "yujin09@77cm.co.kr",
      "password": "J317pQhw",
      "phone": "010-4282-3310",
      "birth": "1988-01-07",
      "dept": "마케팅팀",
      "leftVaca": 9,
      "admin": false,
      "img": "/server/images/profile/54.jpg"
    },
    {
      "userId": 55,
      "name": "송지훈",
      "position": "사원",
      "email": "jihyeon56@77cm.co.kr",
      "password": "WHpM8Nqg",
      "phone": "010-1992-4763",
      "birth": "1963-10-20",
      "dept": "개발팀",
      "leftVaca": 13,
      "admin": false,
      "img": "/server/images/profile/55.jpg"
    },
    {
      "userId": 56,
      "name": "김승현",
      "position": "부장",
      "email": "misuggo@77cm.co.kr",
      "password": "9mPHNCqK",
      "phone": "010-4603-6641",
      "birth": "1996-07-28",
      "dept": "마케팅팀",
      "leftVaca": 6,
      "admin": false,
      "img": "/server/images/profile/56.jpg"
    },
    {
      "userId": 57,
      "name": "오정식",
      "position": "부장",
      "email": "jeongho04@77cm.co.kr",
      "password": "x2WpV6Id",
      "phone": "010-5734-4126",
      "birth": "1964-08-12",
      "dept": "마케팅팀",
      "leftVaca": 0,
      "admin": false,
      "img": "/server/images/profile/57.jpg"
    },
    {
      "userId": 58,
      "name": "이수민",
      "position": "과장",
      "email": "sanghyeon41@77cm.co.kr",
      "password": "PkRTA1Bh",
      "phone": "010-3148-6023",
      "birth": "1987-10-24",
      "dept": "영업팀",
      "leftVaca": 16,
      "admin": false,
      "img": "/server/images/profile/58.jpg"
    },
    {
      "userId": 59,
      "name": "손정희",
      "position": "대리",
      "email": "jeongja41@77cm.co.kr",
      "password": "4XyakaXx",
      "phone": "010-4947-1414",
      "birth": "1964-09-05",
      "dept": "마케팅팀",
      "leftVaca": 2,
      "admin": false,
      "img": "/server/images/profile/59.jpg"
    },
    {
      "userId": 60,
      "name": "서주원",
      "position": "차장",
      "email": "gimmyeongsug@77cm.co.kr",
      "password": "1FkntKgk",
      "phone": "010-2754-6715",
      "birth": "1984-07-25",
      "dept": "마케팅팀",
      "leftVaca": 15,
      "admin": false,
      "img": "/server/images/profile/60.jpg"
    },
    {
      "userId": 61,
      "name": "양현주",
      "position": "차장",
      "email": "seunghyeon15@77cm.co.kr",
      "password": "0aTW9HTt",
      "phone": "010-4125-2285",
      "birth": "1959-01-20",
      "dept": "영업팀",
      "leftVaca": 4,
      "admin": false,
      "img": "/server/images/profile/61.jpg"
    },
    {
      "userId": 62,
      "name": "김은영",
      "position": "차장",
      "email": "mgim@77cm.co.kr",
      "password": "GO2l4XbI",
      "phone": "010-6939-3328",
      "birth": "1963-01-16",
      "dept": "마케팅팀",
      "leftVaca": 14,
      "admin": false,
      "img": "/server/images/profile/62.jpg"
    },
    {
      "userId": 63,
      "name": "이현우",
      "position": "대리",
      "email": "seohyeon77@77cm.co.kr",
      "password": "9SuGVPym",
      "phone": "010-5773-4721",
      "birth": "1979-11-30",
      "dept": "마케팅팀",
      "leftVaca": 13,
      "admin": false,
      "img": "/server/images/profile/63.jpg"
    },
    {
      "userId": 64,
      "name": "허성수",
      "position": "차장",
      "email": "minjunhan@77cm.co.kr",
      "password": "yo4Sz0Vr",
      "phone": "010-3324-7576",
      "birth": "1960-02-19",
      "dept": "인사팀",
      "leftVaca": 17,
      "admin": false,
      "img": "/server/images/profile/64.jpg"
    },
    {
      "userId": 65,
      "name": "이수민",
      "position": "사원",
      "email": "seonghunno@77cm.co.kr",
      "password": "7QEuhVvT",
      "phone": "010-5984-4826",
      "birth": "1984-09-01",
      "dept": "영업팀",
      "leftVaca": 9,
      "admin": false,
      "img": null
    },
    {
      "userId": 66,
      "name": "이예원",
      "position": "사원",
      "email": "soncunja@77cm.co.kr",
      "password": "vl9RcZd7",
      "phone": "010-705-2729",
      "birth": "1980-09-29",
      "dept": "영업팀",
      "leftVaca": 13,
      "admin": false,
      "img": "/server/images/profile/66.jpg"
    },
    {
      "userId": 67,
      "name": "고현주",
      "position": "대리",
      "email": "seongsu66@77cm.co.kr",
      "password": "q3U9Q2Xu",
      "phone": "010-1902-9125",
      "birth": "1979-04-20",
      "dept": "마케팅팀",
      "leftVaca": 9,
      "admin": false,
      "img": "/server/images/profile/67.jpg"
    },
    {
      "userId": 68,
      "name": "김영환",
      "position": "부장",
      "email": "ujin07@77cm.co.kr",
      "password": "h2HutaWm",
      "phone": "010-9767-8944",
      "birth": "2000-08-13",
      "dept": "마케팅팀",
      "leftVaca": 13,
      "admin": false,
      "img": "/server/images/profile/68.jpg"
    },
    {
      "userId": 69,
      "name": "박영숙",
      "position": "사원",
      "email": "yeongil65@77cm.co.kr",
      "password": "o6XhEgKT",
      "phone": "010-3628-5200",
      "birth": "1960-10-31",
      "dept": "마케팅팀",
      "leftVaca": 13,
      "admin": false,
      "img": null
    },
    {
      "userId": 70,
      "name": "이재현",
      "position": "대리",
      "email": "ihyeonju@77cm.co.kr",
      "password": "DO0YvAVl",
      "phone": "010-9906-9823",
      "birth": "2000-07-14",
      "dept": "재무팀",
      "leftVaca": 13,
      "admin": false,
      "img": "/server/images/profile/70.jpg"
    },
    {
      "userId": 71,
      "name": "박영진",
      "position": "과장",
      "email": "fgim@77cm.co.kr",
      "password": "7iUhD5xy",
      "phone": "010-8532-2852",
      "birth": "1958-05-10",
      "dept": "재무팀",
      "leftVaca": 20,
      "admin": false,
      "img": "/server/images/profile/71.jpg"
    },
    {
      "userId": 72,
      "name": "이현준",
      "position": "부장",
      "email": "jangyeongsig@77cm.co.kr",
      "password": "9FiMWivv",
      "phone": "010-5056-1983",
      "birth": "1991-12-02",
      "dept": "인사팀",
      "leftVaca": 9,
      "admin": false,
      "img": "/server/images/profile/72.jpg"
    },
    {
      "userId": 73,
      "name": "윤서윤",
      "position": "대리",
      "email": "byeongceol80@77cm.co.kr",
      "password": "V7P48NOr",
      "phone": "010-9335-9078",
      "birth": "1954-09-29",
      "dept": "인사팀",
      "leftVaca": 10,
      "admin": false,
      "img": "/server/images/profile/73.jpg"
    },
    {
      "userId": 74,
      "name": "박미영",
      "position": "대리",
      "email": "jeonghunbag@77cm.co.kr",
      "password": "Ux3VKGNq",
      "phone": "010-7136-4080",
      "birth": "1987-09-21",
      "dept": "영업팀",
      "leftVaca": 9,
      "admin": false,
      "img": null
    },
    {
      "userId": 75,
      "name": "김정훈",
      "position": "대리",
      "email": "songseungmin@77cm.co.kr",
      "password": "17uBNdhq",
      "phone": "010-5392-3733",
      "birth": "1953-01-02",
      "dept": "마케팅팀",
      "leftVaca": 2,
      "admin": false,
      "img": null
    },
    {
      "userId": 76,
      "name": "고수민",
      "position": "대리",
      "email": "hyeonjubag@77cm.co.kr",
      "password": "QZP1szXu",
      "phone": "010-9666-7747",
      "birth": "1962-09-30",
      "dept": "개발팀",
      "leftVaca": 19,
      "admin": false,
      "img": "/server/images/profile/76.jpg"
    },
    {
      "userId": 77,
      "name": "최경숙",
      "position": "사원",
      "email": "eunseogim@77cm.co.kr",
      "password": "30GbU7dI",
      "phone": "010-8915-5384",
      "birth": "1969-08-14",
      "dept": "영업팀",
      "leftVaca": 13,
      "admin": false,
      "img": null
    },
    {
      "userId": 78,
      "name": "이지우",
      "position": "부장",
      "email": "yejin37@77cm.co.kr",
      "password": "r9SIlf9C",
      "phone": "010-8282-3725",
      "birth": "1980-10-09",
      "dept": "재무팀",
      "leftVaca": 9,
      "admin": false,
      "img": "/server/images/profile/78.jpg"
    },
    {
      "userId": 79,
      "name": "김지혜",
      "position": "대리",
      "email": "gi@77cm.co.kr",
      "password": "9ZsApjTl",
      "phone": "010-6988-5425",
      "birth": "1986-05-25",
      "dept": "개발팀",
      "leftVaca": 9,
      "admin": false,
      "img": "/server/images/profile/79.jpg"
    },
    {
      "userId": 80,
      "name": "한도윤",
      "position": "부장",
      "email": "gimsanghun@77cm.co.kr",
      "password": "3SZ1tOcw",
      "phone": "010-9846-9662",
      "birth": "1985-06-06",
      "dept": "마케팅팀",
      "leftVaca": 2,
      "admin": false,
      "img": "/server/images/profile/80.jpg"
    },
    {
      "userId": 81,
      "name": "강명자",
      "position": "과장",
      "email": "sanghogim@77cm.co.kr",
      "password": "7Xe5Lcue",
      "phone": "010-9585-4254",
      "birth": "1989-11-24",
      "dept": "재무팀",
      "leftVaca": 18,
      "admin": false,
      "img": "/server/images/profile/81.jpg"
    },
    {
      "userId": 82,
      "name": "한지혜",
      "position": "차장",
      "email": "isanghun@77cm.co.kr",
      "password": "4swGReS7",
      "phone": "010-5374-9494",
      "birth": "1978-09-03",
      "dept": "마케팅팀",
      "leftVaca": 4,
      "admin": false,
      "img": "/server/images/profile/82.jpg"
    },
    {
      "userId": 83,
      "name": "황경수",
      "position": "대리",
      "email": "ecoe@77cm.co.kr",
      "password": "m0L7b2av",
      "phone": "010-3213-6336",
      "birth": "1989-12-13",
      "dept": "인사팀",
      "leftVaca": 2,
      "admin": false,
      "img": "/server/images/profile/83.jpg"
    },
    {
      "userId": 84,
      "name": "안아름",
      "position": "사원",
      "email": "sujingim@77cm.co.kr",
      "password": "Fmp6WwtW",
      "phone": "010-6858-1387",
      "birth": "1976-08-17",
      "dept": "영업팀",
      "leftVaca": 14,
      "admin": false,
      "img": "/server/images/profile/84.jpg"
    },
    {
      "userId": 85,
      "name": "김시우",
      "position": "대리",
      "email": "imboram@77cm.co.kr",
      "password": "31YZvUgU",
      "phone": "010-6430-1303",
      "birth": "1988-01-10",
      "dept": "인사팀",
      "leftVaca": 18,
      "admin": false,
      "img": "/server/images/profile/85.jpg"
    },
    {
      "userId": 86,
      "name": "김지민",
      "position": "사원",
      "email": "ijeongsig@77cm.co.kr",
      "password": "6jYMYpdW",
      "phone": "010-3861-7665",
      "birth": "1990-06-07",
      "dept": "개발팀",
      "leftVaca": 8,
      "admin": false,
      "img": "/server/images/profile/86.jpg"
    },
    {
      "userId": 87,
      "name": "이정남",
      "position": "대리",
      "email": "seongsu52@77cm.co.kr",
      "password": "8h0TbBfs",
      "phone": "010-8877-1026",
      "birth": "1954-04-27",
      "dept": "영업팀",
      "leftVaca": 5,
      "admin": false,
      "img": null
    },
    {
      "userId": 88,
      "name": "이하윤",
      "position": "사원",
      "email": "seonghungim@77cm.co.kr",
      "password": "Tn7AuD3a",
      "phone": "010-6844-3974",
      "birth": "1967-01-17",
      "dept": "인사팀",
      "leftVaca": 18,
      "admin": false,
      "img": "/server/images/profile/88.jpg"
    },
    {
      "userId": 89,
      "name": "김아름",
      "position": "차장",
      "email": "eunju36@77cm.co.kr",
      "password": "A63Bb4cu",
      "phone": "010-4484-6569",
      "birth": "1985-01-02",
      "dept": "인사팀",
      "leftVaca": 3,
      "admin": false,
      "img": "/server/images/profile/89.jpg"
    },
    {
      "userId": 90,
      "name": "노예진",
      "position": "대리",
      "email": "vsong@77cm.co.kr",
      "password": "7aUgDxqw",
      "phone": "010-6667-9964",
      "birth": "1991-09-03",
      "dept": "재무팀",
      "leftVaca": 6,
      "admin": false,
      "img": "/server/images/profile/90.jpg"
    },
    {
      "userId": 91,
      "name": "박준혁",
      "position": "사원",
      "email": "gimjeongung@77cm.co.kr",
      "password": "ZC706zOo",
      "phone": "010-7050-2389",
      "birth": "1957-07-27",
      "dept": "영업팀",
      "leftVaca": 0,
      "admin": false,
      "img": "/server/images/profile/91.jpg"
    },
    {
      "userId": 92,
      "name": "윤하윤",
      "position": "차장",
      "email": "gyeongsu93@77cm.co.kr",
      "password": "31RjqxIg",
      "phone": "010-8702-4422",
      "birth": "1974-10-02",
      "dept": "영업팀",
      "leftVaca": 13,
      "admin": false,
      "img": "/server/images/profile/92.jpg"
    },
    {
      "userId": 93,
      "name": "류영희",
      "position": "부장",
      "email": "jieun88@77cm.co.kr",
      "password": "pJ2UU79c",
      "phone": "010-8171-1342",
      "birth": "1970-07-17",
      "dept": "마케팅팀",
      "leftVaca": 4,
      "admin": false,
      "img": "/server/images/profile/93.jpg"
    },
    {
      "userId": 94,
      "name": "노영환",
      "position": "차장",
      "email": "bagyejin@77cm.co.kr",
      "password": "0UfZJcd9",
      "phone": "010-3691-3326",
      "birth": "1969-02-14",
      "dept": "마케팅팀",
      "leftVaca": 14,
      "admin": false,
      "img": "/server/images/profile/94.jpg"
    },
    {
      "userId": 95,
      "name": "이혜진",
      "position": "부장",
      "email": "ci@77cm.co.kr",
      "password": "6XqA26Sp",
      "phone": "010-5956-8601",
      "birth": "1975-12-18",
      "dept": "마케팅팀",
      "leftVaca": 17,
      "admin": false,
      "img": "/server/images/profile/95.jpg"
    },
    {
      "userId": 96,
      "name": "박동현",
      "position": "부장",
      "email": "yejun78@77cm.co.kr",
      "password": "g2zNGUfm",
      "phone": "010-2843-6121",
      "birth": "1998-03-08",
      "dept": "개발팀",
      "leftVaca": 13,
      "admin": false,
      "img": "/server/images/profile/96.jpg"
    },
    {
      "userId": 97,
      "name": "김준서",
      "position": "과장",
      "email": "eunji53@77cm.co.kr",
      "password": "Bi6oKFpL",
      "phone": "010-1577-4044",
      "birth": "1986-10-05",
      "dept": "재무팀",
      "leftVaca": 11,
      "admin": false,
      "img": "/server/images/profile/97.jpg"
    },
    {
      "userId": 98,
      "name": "서현지",
      "position": "과장",
      "email": "gimeunyeong@77cm.co.kr",
      "password": "5Q8CdjHC",
      "phone": "010-7951-6319",
      "birth": "1970-07-11",
      "dept": "재무팀",
      "leftVaca": 10,
      "admin": false,
      "img": "/server/images/profile/98.jpg"
    },
    {
      "userId": 99,
      "name": "윤서윤",
      "position": "과장",
      "email": "yeongilbag@77cm.co.kr",
      "password": "w34wRDdj",
      "phone": "010-4651-3031",
      "birth": "1990-10-29",
      "dept": "영업팀",
      "leftVaca": 13,
      "admin": false,
      "img": null
    },
    {
      "userId": 100,
      "name": "하미경",
      "position": "과장",
      "email": "hyeonsug23@77cm.co.kr",
      "password": "8LoMIHBG",
      "phone": "010-7561-5085",
      "birth": "1957-10-23",
      "dept": "인사팀",
      "leftVaca": 13,
      "admin": false,
      "img": "/server/images/profile/100.jpg"
    },
    {
      "userId": 101,
      "name": "김직원",
      "position": "사원",
      "email": "test1@77cm.co.kr",
      "password": "test1",
      "phone": "010-0012-2122",
      "birth": "1957-10-23",
      "dept": "개발팀",
      "leftVaca": 13,
      "admin": true,
      "img": null
    },
    {
      "userId": 102,
      "name": "최직원",
      "position": "사원",
      "email": "test2@77cm.co.kr",
      "password": "test2",
      "phone": "010-2215-3451",
      "birth": "1957-10-23",
      "dept": "개발팀",
      "leftVaca": 13,
      "admin": false,
      "img": null
    }
  ]
}
